maweng/__init__.py
maweng/app.py
maweng/cli.py
maweng/config.py
maweng/exceptions.py
maweng/middleware.py
maweng/request.py
maweng/response.py
maweng/testing.py
maweng/view.py
maweng/cli_modules/__init__.py
maweng/cli_modules/build.py
maweng/cli_modules/check.py
maweng/cli_modules/database.py
maweng/cli_modules/generators.py
maweng/cli_modules/info.py
maweng/cli_modules/runner.py
maweng/cli_modules/templates.py
maweng/cli_modules/testing.py
maweng/orm/__init__.py
maweng/orm/database.py
maweng/orm/field.py
maweng/orm/model.py
maweng/orm/query.py
maweng/orm/relationship.py
maweng-0.2.2.dist-info/licenses/LICENSE
maweng-0.2.2.dist-info/METADATA
maweng-0.2.2.dist-info/WHEEL
maweng-0.2.2.dist-info/entry_points.txt
maweng-0.2.2.dist-info/top_level.txt
maweng-0.2.2.dist-info/RECORD
